LICENSE
MANIFEST.in
README.md
VERSION
requirements.txt
setup.py
texta_tagger/__init__.py
texta_tagger/exceptions.py
texta_tagger/pipeline.py
texta_tagger/tagger.py
texta_tagger/tagging_report.py
texta_tagger.egg-info/PKG-INFO
texta_tagger.egg-info/SOURCES.txt
texta_tagger.egg-info/dependency_links.txt
texta_tagger.egg-info/requires.txt
texta_tagger.egg-info/top_level.txt