Metadata-Version: 2.1
Name: texta-tagger
Version: 2.1.2
Summary: texta-tagger
Home-page: https://git.texta.ee/texta/texta-tagger-python
Author: TEXTA
Author-email: info@texta.ee
License: GPLv3
Platform: UNKNOWN
Provides-Extra: mlp
Provides-Extra: embedding
